flet_gradient_text/__init__.py
flet_gradient_text-1.1.0.dist-info/licenses/LICENSE
flet_gradient_text-1.1.0.dist-info/METADATA
flet_gradient_text-1.1.0.dist-info/WHEEL
flet_gradient_text-1.1.0.dist-info/top_level.txt
flet_gradient_text-1.1.0.dist-info/RECORD
