Metadata-Version: 2.4
Name: flet_gradient_text
Version: 1.1.0
Summary: A flet component for gradient & animated text
Author-email: Benit Mulindwa <mulindwabenit@gmail.com>
License: MIT
Project-URL: Homepage, https://github.com/Benitmulindwa/flet_gradient_text
Classifier: Programming Language :: Python :: 3
Classifier: License :: OSI Approved :: MIT License
Classifier: Operating System :: OS Independent
Requires-Python: >=3.8
License-File: LICENSE
Requires-Dist: flet
Dynamic: license-file
